{
  "Builds": [
    {
      "StarterItem": "19677",
      "Items": [
        "19679",
        "7784",
        "24103",
        "15582",
        "9128",
        "9859"
      ]
    },
    {
      "StarterItem": "19508",
      "Items": [
        "19509",
        "15725",
        "15582",
        "24103",
        "18179",
        "9128"
      ]
    },
    {
      "StarterItem": "19496",
      "Items": [
        "19512",
        "15725",
        "24190",
        "24103",
        "18179",
        "9860"
      ]
    }
  ],
  "Relics": [
    "21572",
    "21545"
  ]
}