{
  "Builds": [
    {
      "StarterItem": "15767",
      "Items": [
        "15767",
        "7641",
        "17090",
        "24189",
        "7593",
        "10482"
      ]
    },
    {
      "StarterItem": "23146",
      "Items": [
        "23146",
        "17090",
        "23870",
        "7575",
        "10482",
        "8560"
      ]
    },
    {
      "StarterItem": "19924",
      "Items": [
        "19924",
        "17090",
        "16544",
        "24189",
        "10482",
        "7593"
      ]
    },
    {
      "StarterItem": "17090",
      "Items": [
        "17090",
        "14178",
        "19924",
        "7593",
        "24189",
        "10482"
      ]
    }
  ],
  "Relics": [
    "21568",
    "21575"
  ]
}