{
  "Builds": [
    {
      "StarterItem": "19508",
      "Items": [
        "19508",
        "15725",
        "24103",
        "9128",
        "18179",
        "9850"
      ]
    },
    {
      "StarterItem": "19677",
      "Items": [
        "19677",
        "12670",
        "24103",
        "7597",
        "22941",
        "15582"
      ]
    },
    {
      "StarterItem": "7784",
      "Items": [
        "7784",
        "23871",
        "15725",
        "15582",
        "18179",
        "9128"
      ]
    }
  ],
  "Relics": [
    "21572",
    "21545"
  ]
}